vplexapi/__init__.py
vplexapi/api_client.py
vplexapi/configuration.py
vplexapi/rest.py
vplexapi/api/__init__.py
vplexapi/api/aggregate_api.py
vplexapi/api/amp_api.py
vplexapi/api/bulk_api.py
vplexapi/api/certificates_api.py
vplexapi/api/cluster_witness_api.py
vplexapi/api/clusters_api.py
vplexapi/api/consistency_group_api.py
vplexapi/api/data_migration_api.py
vplexapi/api/devices_api.py
vplexapi/api/director_api.py
vplexapi/api/director_ports_api.py
vplexapi/api/distributed_storage_api.py
vplexapi/api/engine_api.py
vplexapi/api/exports_api.py
vplexapi/api/extent_api.py
vplexapi/api/hardware_ports_api.py
vplexapi/api/health_api.py
vplexapi/api/jobs_api.py
vplexapi/api/licenses_api.py
vplexapi/api/logger_api.py
vplexapi/api/logging_volume_api.py
vplexapi/api/logical_units_api.py
vplexapi/api/maps_api.py
vplexapi/api/meta_volume_api.py
vplexapi/api/metadata_backup_api.py
vplexapi/api/monitors_api.py
vplexapi/api/permissions_api.py
vplexapi/api/recoverpoint_api.py
vplexapi/api/storage_array_api.py
vplexapi/api/storage_group_api.py
vplexapi/api/storage_pool_api.py
vplexapi/api/storage_volume_api.py
vplexapi/api/system_alert_api.py
vplexapi/api/system_config_api.py
vplexapi/api/token_api.py
vplexapi/api/version_api.py
vplexapi/api/virtual_volume_api.py
vplexapi/models/__init__.py
vplexapi/models/admin_state.py
vplexapi/models/aggregate.py
vplexapi/models/aggregates.py
vplexapi/models/amp_payload.py
vplexapi/models/array_management_provider.py
vplexapi/models/bulk_response.py
vplexapi/models/bulk_response_tasks.py
vplexapi/models/certificate.py
vplexapi/models/certificate_payload.py
vplexapi/models/cg_resume_payload.py
vplexapi/models/claim_payload.py
vplexapi/models/cluster.py
vplexapi/models/cluster_witness.py
vplexapi/models/cluster_witness_components.py
vplexapi/models/com_status.py
vplexapi/models/communication_status.py
vplexapi/models/connectivity_status.py
vplexapi/models/consistency_group.py
vplexapi/models/consistency_group_operational_status.py
pjtchandra-1.0.0.2.dist-info/LICENSE
pjtchandra-1.0.0.2.dist-info/METADATA
pjtchandra-1.0.0.2.dist-info/WHEEL
pjtchandra-1.0.0.2.dist-info/top_level.txt
pjtchandra-1.0.0.2.dist-info/RECORD
