Metadata-Version: 2.1
Name: pjtchandra
Version: 1.0.0.2
Summary: VPlex REST API
Home-page: https://github.com/dell/python-vplex
Author-email: chandraprakash.boinapally@gmail.com
License: UNKNOWN
Keywords: Swagger,VPlex REST API
Platform: UNKNOWN
Requires-Dist: certifi
Requires-Dist: python-dateutil
Requires-Dist: six (>=1.10)
Requires-Dist: urllib3 (>=1.15)
